apistar_prometheus/__init__.py
apistar_prometheus/components.py
apistar_prometheus/endpoints.py
apistar_prometheus/handlers.py
apistar_prometheus/hooks.py
apistar_prometheus-0.6.0.dist-info/DESCRIPTION.rst
apistar_prometheus-0.6.0.dist-info/METADATA
apistar_prometheus-0.6.0.dist-info/RECORD
apistar_prometheus-0.6.0.dist-info/WHEEL
apistar_prometheus-0.6.0.dist-info/metadata.json
apistar_prometheus-0.6.0.dist-info/top_level.txt
