Metadata-Version: 2.0
Name: apistar-prometheus
Version: 0.6.0
Summary: A Prometheus component for API Star.
Home-page: UNKNOWN
Author: UNKNOWN
Author-email: UNKNOWN
License: UNKNOWN
Platform: UNKNOWN
Requires-Dist: apistar (>=0.5)
Requires-Dist: prometheus-client (>=0.0.20)
